{
    "baselines": [
        {
            "blob": "Qke1bLghyVVCcFjVuBYLkkKMb424Hk+D",
            "detector": "H3"
        },
        {
            "blob": "Qke1bLhv3GZCcFjVuGxan0KMb424dMG8",
            "detector": "H1"
        },
        {
            "blob": "Qke1bLjCHppCcFjVuL7hT0KMb424v2u8",
            "detector": "L1"
        },
        {
            "blob": "Qke1bLflwvlCcFjVt+SNSkKMb4237Y9S",
            "detector": "L3"
        },
        {
            "blob": "Qke1bLwFePtCcFjVvAVz+kKMb428BX3f",
            "detector": "L5"
        }
    ],
    "commit": "f86587f820a44d6c6398ab6bb44cd2a0af5c0e2d",
    "encoding": "base64",
    "format": ">ff",
    "signals": [
        {
            "blob": "Qbjpn7gLSJVCCJGKuBRYMg==",
            "detector": "H3",
            "isotope": "Ar40"
        },
        {
            "blob": "Qbjpn7h0N59CCJGKuHh/jA==",
            "detector": "H1",
            "isotope": "Ar39"
        },
        {
            "blob": "Qbjpn7jExLZCCJGKuMb3/A==",
            "detector": "L1",
            "isotope": "Ar38"
        },
        {
            "blob": "Qbjpn7fyUmRCCJGKt+/v6g==",
            "detector": "L3",
            "isotope": "Ar37"
        },
        {
            "blob": "Qbjpn7wFgjBCCJGKvAWFUg==",
            "detector": "L5",
            "isotope": "Ar36"
        }
    ],
    "sniffs": [
        {
            "blob": null,
            "detector": "H3",
            "isotope": "Ar40"
        },
        {
            "blob": null,
            "detector": "H1",
            "isotope": "Ar39"
        },
        {
            "blob": null,
            "detector": "L1",
            "isotope": "Ar38"
        },
        {
            "blob": null,
            "detector": "L3",
            "isotope": "Ar37"
        },
        {
            "blob": null,
            "detector": "L5",
            "isotope": "Ar36"
        }
    ]
}