{
    "Ar36": {
        "error": 3.457037816060839e-07,
        "error_type": "",
        "fit": "previous",
        "references": [
            {
                "exclude": false,
                "record_id": "ba-01-n-10909"
            }
        ],
        "value": -3.141195156922648e-06
    },
    "Ar37": {
        "error": 2.1893237052718884e-07,
        "error_type": "",
        "fit": "previous",
        "references": [
            {
                "exclude": false,
                "record_id": "ba-01-n-10909"
            }
        ],
        "value": 5.244685608515554e-07
    },
    "Ar38": {
        "error": 2.5218771227232204e-07,
        "error_type": "",
        "fit": "previous",
        "references": [
            {
                "exclude": false,
                "record_id": "ba-01-n-10909"
            }
        ],
        "value": -1.0734815429765902e-07
    },
    "Ar39": {
        "error": 2.6044065816962367e-07,
        "error_type": "",
        "fit": "previous",
        "references": [
            {
                "exclude": false,
                "record_id": "ba-01-n-10909"
            }
        ],
        "value": 1.4237163244967924e-06
    },
    "Ar40": {
        "error": 1.2372161549145213e-06,
        "error_type": "",
        "fit": "previous",
        "references": [
            {
                "exclude": false,
                "record_id": "ba-01-n-10909"
            }
        ],
        "value": 3.733867121949332e-05
    }
}