{
    "Ar36": {
        "error": 2.9778035467635234e-07,
        "error_type": "",
        "fit": "previous",
        "references": [
            {
                "exclude": false,
                "record_id": "ba-01-n-10129"
            }
        ],
        "value": 5.594617755151979e-07
    },
    "Ar37": {
        "error": 2.1613244542386078e-07,
        "error_type": "",
        "fit": "previous",
        "references": [
            {
                "exclude": false,
                "record_id": "ba-01-n-10129"
            }
        ],
        "value": 8.084660627015609e-07
    },
    "Ar38": {
        "error": 2.0033857673003734e-07,
        "error_type": "",
        "fit": "previous",
        "references": [
            {
                "exclude": false,
                "record_id": "ba-01-n-10129"
            }
        ],
        "value": 4.788968912652268e-07
    },
    "Ar39": {
        "error": 2.739186487620504e-07,
        "error_type": "",
        "fit": "previous",
        "references": [
            {
                "exclude": false,
                "record_id": "ba-01-n-10129"
            }
        ],
        "value": 2.9322737089348014e-06
    },
    "Ar40": {
        "error": 2.2600000379464107e-06,
        "error_type": "",
        "fit": "previous",
        "references": [
            {
                "exclude": false,
                "record_id": "ba-01-n-10129"
            }
        ],
        "value": 0.00012323717041101025
    }
}